hcost/__init__.py
hcost/business.py
hcost/models.py
hcost/utils.py
hcost-0.1.0.dist-info/COPYING
hcost-0.1.0.dist-info/WHEEL
hcost-0.1.0.dist-info/METADATA
hcost-0.1.0.dist-info/RECORD
